flake8_ecocode/__init__.py
flake8_ecocode/plugin.py
flake8_ecocode/types.py
flake8_ecocode/rules/__init__.py
flake8_ecocode/rules/base.py
flake8_ecocode/rules/ec_35.py
flake8_ecocode/rules/ec_404.py
flake8_ecocode-0.1.3.dist-info/METADATA
flake8_ecocode-0.1.3.dist-info/WHEEL
flake8_ecocode-0.1.3.dist-info/RECORD
