Metadata-Version: 2.3
Name: flake8-ecocode
Version: 0.1.3
Summary: Ecocode plugin for Flask8
Project-URL: Homepage, https://github.com/abilian/flake8-ecocode
Project-URL: Repository, https://github.com/abilian/flake8-ecocode
Author-email: Stefane Fermigier <sf@abilian.com>
License-Expression: GPL-3.0
Requires-Python: <4.0,>=3.10
Requires-Dist: devtools<0.13.0,>=0.12.2
Requires-Dist: flake8<8.0.0,>=7.1.1
